financeager_flask/__init__.py
financeager_flask/exceptions.py
financeager_flask/flask.py
financeager_flask/httprequests.py
financeager_flask/main.py
financeager_flask/offline.py
financeager_flask/resources.py
financeager_flask-1.1.0.dist-info/LICENSE
financeager_flask-1.1.0.dist-info/METADATA
financeager_flask-1.1.0.dist-info/WHEEL
financeager_flask-1.1.0.dist-info/entry_points.txt
financeager_flask-1.1.0.dist-info/top_level.txt
financeager_flask-1.1.0.dist-info/RECORD
