Metadata-Version: 2.1
Name: financeager-flask
Version: 1.1.0
Summary: Plugin to use flask as backend for financeager
Author-email: Philipp Metzner <beth.aleph@yahoo.de>
License: GPLv3
Project-URL: Bug Tracker, https://github.com/pylipp/financeager-flask/issues
Project-URL: Documentation, https://github.com/pylipp/financeager-flask
Project-URL: Homepage, https://github.com/pylipp/financeager-flask
Project-URL: Source Code, https://github.com/pylipp/financeager-flask
Keywords: commandline,finances
Classifier: Development Status :: 3 - Alpha
Classifier: Environment :: Console
Classifier: Intended Audience :: End Users/Desktop
Classifier: Intended Audience :: Other Audience
Classifier: License :: OSI Approved :: GNU General Public License v3 (GPLv3)
Classifier: Operating System :: Unix
Classifier: Programming Language :: Python :: 3.8
Classifier: Programming Language :: Python :: 3.9
Classifier: Programming Language :: Python :: 3.10
Classifier: Topic :: Office/Business :: Financial
Classifier: Topic :: Database
Classifier: Topic :: Utilities
License-File: LICENSE
Requires-Dist: financeager (<1.4.0,>=1.1.0)
Requires-Dist: Flask (>=1.0.2)
Requires-Dist: Flask-RESTful (>=0.3.5)
Requires-Dist: requests (>=2.20.0)
Provides-Extra: develop
Requires-Dist: black (==23.3.0) ; extra == 'develop'
Requires-Dist: coverage (==7.2.7) ; extra == 'develop'
Requires-Dist: flake8 (==6.0.0) ; extra == 'develop'
Requires-Dist: flake8-pyproject (==1.2.3) ; extra == 'develop'
Requires-Dist: gitlint-core (==0.19.1) ; extra == 'develop'
Requires-Dist: isort (==5.12.0) ; extra == 'develop'
Requires-Dist: pre-commit (==3.3.3) ; extra == 'develop'
Provides-Extra: packaging
Requires-Dist: build ; extra == 'packaging'
Requires-Dist: twine (>=1.11) ; extra == 'packaging'
